inaturalist_to_sqlite/__init__.py
inaturalist_to_sqlite/cli.py
inaturalist_to_sqlite/utils.py
inaturalist_to_sqlite-0.2.1.dist-info/LICENSE
inaturalist_to_sqlite-0.2.1.dist-info/METADATA
inaturalist_to_sqlite-0.2.1.dist-info/WHEEL
inaturalist_to_sqlite-0.2.1.dist-info/entry_points.txt
inaturalist_to_sqlite-0.2.1.dist-info/top_level.txt
inaturalist_to_sqlite-0.2.1.dist-info/RECORD
