Metadata-Version: 2.1
Name: inaturalist-to-sqlite
Version: 0.2.1
Summary: Create a SQLite database containing your observation history from iNaturalist
Home-page: https://github.com/dogsheep/inaturalist-to-sqlite
Author: Simon Willison
License: Apache License, Version 2.0
Platform: UNKNOWN
Requires-Dist: sqlite-utils (>=2.0)
Requires-Dist: click
Requires-Dist: requests
Provides-Extra: test
Requires-Dist: pytest ; extra == 'test'
